Metadata-Version: 1.1
Name: pidproxyd
Version: 0.1.0
Summary: A pidproxy for supervisord that supports daemonized processes.
Home-page: https://github.com/ajpen/pidproxyd
Author: Anfernee Jervis
Author-email: anferneejervis@gmail.com
License: UNKNOWN
Platform: UNKNOWN
Classifier: Development Status :: 2 - Pre-Alpha
Classifier: Programming Language :: Python
Classifier: Programming Language :: Python :: 2
Classifier: Programming Language :: Python :: 2.7
Classifier: Programming Language :: Python :: 3
Classifier: Programming Language :: Python :: 3.4
Classifier: Programming Language :: Python :: 3.5
